smbprotocol_legacy/__init__.py
smbprotocol_legacy/connection.py
smbprotocol_legacy/create_contexts.py
smbprotocol_legacy/exceptions.py
smbprotocol_legacy/ioctl.py
smbprotocol_legacy/open.py
smbprotocol_legacy/query_info.py
smbprotocol_legacy/security_descriptor.py
smbprotocol_legacy/session.py
smbprotocol_legacy/spnego.py
smbprotocol_legacy/structure.py
smbprotocol_legacy/transport.py
smbprotocol_legacy/tree.py
smbprotocol_legacy/version.py
smbprotocol_legacy-0.1.1.dist-info/LICENSE
smbprotocol_legacy-0.1.1.dist-info/METADATA
smbprotocol_legacy-0.1.1.dist-info/WHEEL
smbprotocol_legacy-0.1.1.dist-info/top_level.txt
smbprotocol_legacy-0.1.1.dist-info/RECORD
